ease_sqlite/Sqdb.py
ease_sqlite/Squtils.py
ease_sqlite/__init__.py
ease_sqlite-1.0.5.dist-info/METADATA
ease_sqlite-1.0.5.dist-info/WHEEL
ease_sqlite-1.0.5.dist-info/top_level.txt
ease_sqlite-1.0.5.dist-info/RECORD
