Metadata-Version: 2.1
Name: ease-sqlite
Version: 1.0.5
Summary: 一个简单的sqlite工具，可以简单的建表以及做sql操作
Home-page: https://gitee.com/XBCoder/easy-sqlite-tools
License: UNKNOWN
Project-URL: Documentation, https://gitee.com/XBCoder/easy-sqlite-tools
Project-URL: Source Code, https://gitee.com/XBCoder/easy-sqlite-tools
Keywords: sqlite tools easy
Platform: UNKNOWN
